{
	"name": "pipeline1",
	"properties": {
		"activities": [
			{
				"name": "file_date",
				"type": "AppendVariable",
				"dependsOn": [],
				"userProperties": [],
				"typeProperties": {
					"variableName": "date",
					"value": {
						"value": "@utcnow('yyyyMMdd')",
						"type": "Expression"
					}
				}
			},
			{
				"name": "Copy data1",
				"type": "Copy",
				"dependsOn": [
					{
						"activity": "file_date",
						"dependencyConditions": [
							"Succeeded"
						]
					}
				],
				"policy": {
					"timeout": "0.12:00:00",
					"retry": 0,
					"retryIntervalInSeconds": 30,
					"secureOutput": false,
					"secureInput": false
				},
				"userProperties": [],
				"typeProperties": {
					"source": {
						"type": "RestSource",
						"httpRequestTimeout": "00:01:40",
						"requestInterval": "00.00:00:00.010",
						"requestMethod": "GET",
						"paginationRules": {
							"supportRFC5988": "true"
						}
					},
					"sink": {
						"type": "JsonSink",
						"storeSettings": {
							"type": "AzureBlobFSWriteSettings"
						},
						"formatSettings": {
							"type": "JsonWriteSettings"
						}
					},
					"enableStaging": false
				},
				"inputs": [
					{
						"referenceName": "ls_rest_api_clima",
						"type": "DatasetReference"
					}
				],
				"outputs": [
					{
						"referenceName": "ls_json_api_clima_destino",
						"type": "DatasetReference"
					}
				]
			}
		],
		"variables": {
			"date": {
				"type": "Array"
			}
		},
		"annotations": [],
		"lastPublishTime": "2024-02-14T17:31:05Z"
	},
	"type": "Microsoft.DataFactory/factories/pipelines"
}